README.md
setup.py
k40nano/Connection.py
k40nano/FileWriteConnection.py
k40nano/LaserSpeed.py
k40nano/MockUsb.py
k40nano/NanoConnection.py
k40nano/NanoPlotter.py
k40nano/NanoUsb.py
k40nano/Plotter.py
k40nano/PngPlotter.py
k40nano/PngRaster.py
k40nano/PrintConnection.py
k40nano/SvgPlotter.py
k40nano/__init__.py
k40nano.egg-info/PKG-INFO
k40nano.egg-info/SOURCES.txt
k40nano.egg-info/dependency_links.txt
k40nano.egg-info/requires.txt
k40nano.egg-info/top_level.txt
test/test_laser_speeds.py
test/test_nanoplotter.py