Metadata-Version: 2.1
Name: k40nano
Version: 0.2.0
Summary: Low Level K40 Control
Home-page: https://github.com/K40Nano/K40Nano
Author: Scorch / Tatarize
Author-email: tatarize@gmail.com
License: UNKNOWN
Platform: UNKNOWN
Classifier: Programming Language :: Python :: 2
Classifier: Programming Language :: Python :: 3
Classifier: License :: OSI Approved :: GNU General Public License v2 (GPLv2)
Classifier: Operating System :: OS Independent
